examplecurves/__init__.py
examplecurves/main.py
examplecurves/resources/__init__.py
examplecurves/resources/linear_curves.json
tests/__init__.py
tests/load_test.py
tests/plot_test.py
examplecurves-1.0.0.dist-info/LICENSE
examplecurves-1.0.0.dist-info/METADATA
examplecurves-1.0.0.dist-info/WHEEL
examplecurves-1.0.0.dist-info/top_level.txt
examplecurves-1.0.0.dist-info/RECORD
