Metadata-Version: 2.1
Name: examplecurves
Version: 1.0.0
Summary: Module for providing exemplary, reproducible curves for testing and debugging.
Home-page: https://gitlab.com/david.scheliga/examplecurves
Author: David Scheliga
License: GNU General Public License V3 (GPLv3)
Project-URL: Documentation, https://examplecurves.readthedocs.io/en/latest/
Project-URL: Source Code Repository, https://gitlab.com/david.scheliga/examplecurves
Keywords: curve,testing,debugging,engineering
Platform: UNKNOWN
Classifier: Development Status :: 5 - Production/Stable
Classifier: License :: OSI Approved :: GNU General Public License v3 (GPLv3)
Classifier: Operating System :: OS Independent
Classifier: Programming Language :: Python
Classifier: Programming Language :: Python :: 3.6
Classifier: Programming Language :: Python :: 3.7
Classifier: Programming Language :: Python :: 3.8
Classifier: Programming Language :: Python :: 3.9
Requires-Python: >=3.6
Requires-Dist: pandas (>=1.0.3)
Requires-Dist: numpy (>=1.17.0)
Requires-Dist: dicthandling (>=0.2b2)
Requires-Dist: matplotlib (>=3.0.0)
Requires-Dist: scipy (>=0.19.0)
Requires-Dist: importlib-resources ; python_version == "3.6"
